tox_recreate_hook/__init__.py
tox_recreate_hook/py.typed
tox_recreate_hook/hooks.py
tox_recreate_hook-0.1.1.dist-info/METADATA
tox_recreate_hook-0.1.1.dist-info/top_level.txt
tox_recreate_hook-0.1.1.dist-info/WHEEL
tox_recreate_hook-0.1.1.dist-info/LICENSE
tox_recreate_hook-0.1.1.dist-info/entry_points.txt
tox_recreate_hook-0.1.1.dist-info/RECORD
