Metadata-Version: 2.1
Name: tox-recreate-hook
Version: 0.1.1
Summary: (experimental) Allows hooks to be defined which are called when recreating a tox testenv.
Author-email: Dominic Davis-Foster <dominic@davis-foster.co.uk>
License: MIT
Keywords: tox
Home-page: https://github.com/python-coincidence/tox-recreate-hook
Project-URL: Issue Tracker, https://github.com/python-coincidence/tox-recreate-hook/issues
Project-URL: Source Code, https://github.com/python-coincidence/tox-recreate-hook
Project-URL: Documentation, https://tox-recreate-hook.readthedocs.io/en/latest
Platform: Windows
Platform: macOS
Platform: Linux
Classifier: Development Status :: 3 - Alpha
Classifier: Framework :: tox
Classifier: Intended Audience :: Developers
Classifier: License :: OSI Approved :: MIT License
Classifier: Operating System :: OS Independent
Classifier: Programming Language :: Python
Classifier: Programming Language :: Python :: 3 :: Only
Classifier: Programming Language :: Python :: 3.7
Classifier: Programming Language :: Python :: 3.8
Classifier: Programming Language :: Python :: 3.9
Classifier: Programming Language :: Python :: Implementation :: CPython
Classifier: Topic :: Software Development :: Quality Assurance
Classifier: Topic :: Software Development :: Testing
Classifier: Topic :: Software Development :: Testing :: Unit
Classifier: Typing :: Typed
Requires-Python: >=3.7
Requires-Dist: domdf-python-tools>=2.8.0
Requires-Dist: first>=2.0.2
Requires-Dist: pluggy>=0.13.1
Requires-Dist: tox>=3.21.0
